calitp_data_analysis/__init__.py
calitp_data_analysis/calitp_color_palette.py
calitp_data_analysis/gcs_geopandas.py
calitp_data_analysis/gcs_pandas.py
calitp_data_analysis/geography_utils.py
calitp_data_analysis/magics.py
calitp_data_analysis/sql.py
calitp_data_analysis/styleguide.py
calitp_data_analysis/utils.py
calitp_data_analysis-2026.1.30.dist-info/METADATA
calitp_data_analysis-2026.1.30.dist-info/WHEEL
calitp_data_analysis-2026.1.30.dist-info/RECORD
