Metadata-Version: 2.4
Name: calitp-data-analysis
Version: 2026.1.30
Summary: Shared code for querying Cal-ITP data in notebooks, primarily.
Requires-Python: >=3.11.0, <3.12.0
Classifier: Programming Language :: Python :: 3
Classifier: Programming Language :: Python :: 3.11
Requires-Dist: altair (>=5.1.1,<6.0.0)
Requires-Dist: black (==24.10.0)
Requires-Dist: dask (>=2024.10.0,<2025.4.0)
Requires-Dist: dask-geopandas (>=0.2.0,<0.3.0)
Requires-Dist: gcsfs (==2024.5.0)
Requires-Dist: geopandas (>=0.14.0,<0.15.0)
Requires-Dist: gtfs-segments (==2.1.7)
Requires-Dist: ipython (>=8.9.0,<9.0.0)
Requires-Dist: jinja2 (>=3.1.3,<4.0.0)
Requires-Dist: pandas (>=2.0.0,<3.0.0)
Requires-Dist: pandas-gbq (>=0.19.1,<0.20.0)
Requires-Dist: pyairtable (==2.2.2)
Requires-Dist: requests (>=2.31.0,<3.0.0)
Requires-Dist: shapely (>=2.0.1,<3.0.0)
Requires-Dist: sqlalchemy (>=2.0.0,<3.0.0)
Requires-Dist: sqlalchemy-bigquery (>=1.6.1,<2.0.0)
